minute_count/__init__.py
minute_count/__main__.py
minute_count/minute_count.py
minute_count/terminal_formatting.py
minute_count/time_formatting.py
minute_count/version.py
minute_count-2025.6.4.dist-info/METADATA
minute_count-2025.6.4.dist-info/WHEEL
minute_count-2025.6.4.dist-info/entry_points.txt
minute_count-2025.6.4.dist-info/licenses/LICENSE.txt
minute_count-2025.6.4.dist-info/RECORD
